test_auto_publish_lib/__init__.py
test_auto_publish_lib/get_info.py
test_auto_publish_lib-0.1.0.dist-info/METADATA
test_auto_publish_lib-0.1.0.dist-info/WHEEL
test_auto_publish_lib-0.1.0.dist-info/top_level.txt
test_auto_publish_lib-0.1.0.dist-info/RECORD
